assignmentxblock/__init__.py
assignmentxblock/assignmentxblock.py
assignmentxblock/config.py
assignmentxblock/fileupload.py
assignmentxblock/uploaders.py
assignmentxblock/static/README.txt
assignmentxblock/static/css/assignmentxblock.css
assignmentxblock/static/css/studio_view.css
assignmentxblock/static/js/studio_view.js
assignmentxblock/static/js/unit_1.js
assignmentxblock/static/js/unit_2.js
assignmentxblock/templates/author_view.html
assignmentxblock/templates/base.html
assignmentxblock/templates/error.html
assignmentxblock/templates/has_not_submitted.html
assignmentxblock/templates/studio_view.html
assignmentxblock/templates/submitted.html
assignmentxblock/templates/unit_1.html
assignmentxblock/templates/unit_2.html
assignmentxblock/templates/components/common_message.html
assignmentxblock/templates/components/submission_history.html
assignmentxblock/templates/components/submission_response.html
assignmentxblock/templates/components/submission_status.html
assignmentxblock/templates/components/submit_project.html
assignmentxblock/translations/README.txt
assignmentxblock/translations/en/LC_MESSAGES/django.mo
assignmentxblock/translations/en/LC_MESSAGES/django.po
assignmentxblock/translations/en/LC_MESSAGES/djangojs.mo
assignmentxblock/translations/en/LC_MESSAGES/djangojs.po
assignmentxblock/translations/vi/LC_MESSAGES/django.mo
assignmentxblock/translations/vi/LC_MESSAGES/django.po
assignmentxblock/translations/vi/LC_MESSAGES/djangojs.mo
assignmentxblock/translations/vi/LC_MESSAGES/djangojs.po
assignmentxblock_xblock-0.3.7.dev0.dist-info/METADATA
assignmentxblock_xblock-0.3.7.dev0.dist-info/WHEEL
assignmentxblock_xblock-0.3.7.dev0.dist-info/entry_points.txt
assignmentxblock_xblock-0.3.7.dev0.dist-info/top_level.txt
assignmentxblock_xblock-0.3.7.dev0.dist-info/RECORD
