Metadata-Version: 2.1
Name: assignmentxblock-xblock
Version: 0.3.7.dev0
Summary: Assignment XBlock
Home-page: UNKNOWN
License: UNKNOWN
Platform: UNKNOWN
Requires-Dist: XBlock
